{"title":"페스티벌 라이프 ─ 국내공연","url":"https://festivallife.kr/concert","favicon":"https://cdn.imweb.me/thumbnail/20200309/d75fd675e7114.png","elements":[{"title":"공지\n\t\t\t\t\t\t\t\t\t\t\t\t\t\t\t\t\t\t\t\n\t\t\t\t\t\t\t\t\t\t\t\n\t\t\t\t\t\t\t\t\t\t\n\t\t\t\t\t\t\t\t\t\t\t\t\t\t\t\t\t\tMPMG WEEK 2024 : 78LIVE - 구만(9.10000)\t\t\t\t\t\t\t\t\t\t\t\t\t\t\t\t\t\t\tN","contents":"<div class=\"ma-item _post_item_wrap\" style=\"padding: 15px;\">\n\t\t\t\t<div class=\"card  _card\" style=\"  background-size: cover; background-position: 50% 50%;\">\n\t\t\t\t\t<span class=\"holder blocked\" style=\"cursor:pointer;\">\n\t\t\t\t\t\t\t\t\t\t\t\t<a class=\"post_link_wrap _fade_link\" href=\"/concert/?q=YToxOntzOjEyOiJrZXl3b3JkX3R5cGUiO3M6MzoiYWxsIjt9&amp;bmode=view&amp;idx=17625685&amp;t=board\">\n\t\t\t\t\t\t\t<div class=\"card_wrapper card-thumbnail-wrap \" style=\"background-image: url(https://cdn.imweb.me/thumbnail/20240117/1dce720885675.gif);  background-size: cover; background-position: 50% 50%;\">\n\t\t\t\t\t\t\t\t<div class=\"card-head _card_head _img_wrap\" style=\"height: 387px;\">\n\t\t\t\t\t\t\t\t\t<span>\n\t\t\t\t\t\t\t\t\t\t\t\t\t\t\t\t\t\t\t</span>\n\t\t\t\t\t\t\t\t</div>\n\t\t\t\t\t\t\t</div>\n\t\t\t\t\t\t\t<div class=\"card-body _card_body list-group\">\n\t\t\t\t\t\t\t\t<div class=\"title title-block\">\n\t\t\t\t\t\t\t\t\t<em class=\"notice-block\" style=\"display: none\">공지</em>\n\t\t\t\t\t\t\t\t\t\t\t\t\t\t\t\t\t\t\t<span>\n\t\t\t\t\t\t\t\t\t\t\t<em style=\"padding-right:5px;color:;display: none\"></em>\n\t\t\t\t\t\t\t\t\t\t</span>\n\t\t\t\t\t\t\t\t\t\t\t\t\t\t\t\t\t\tMPMG WEEK 2024 : 78LIVE - 구만(9.10000)\t\t\t\t\t\t\t\t\t\t\t\t\t\t\t\t\t\t\t<span class=\"icons\"><em class=\"addon-badge\">N</em></span>\n\t\t\t\t\t\t\t\t\t<!--\t\t\t\t\t\t\t\t\t--><!--\t\t\t\t\t\t\t\t\t\t<span class=\"icons text-20 \"><i aria-hidden=\"true\" class=\"icon-picture\"></i></span>-->\n\t\t\t\t\t\t\t\t\t<!--\t\t\t\t\t\t\t\t\t--><!--\t\t\t\t\t\t\t\t\t--><!--\t\t\t\t\t\t\t\t\t\t<span class=\"icons text-20\"><i aria-hidden=\"true\" class=\"icon-folder\"></i></span>-->\n\t\t\t\t\t\t\t\t\t<!--\t\t\t\t\t\t\t\t\t--><!--\t\t\t\t\t\t\t\t\t--><!--\t\t\t\t\t\t\t\t\t\t<span class=\"icons text-20\"><i aria-hidden=\"true\" class=\"icon-camrecorder\"></i></span>-->\n\t\t\t\t\t\t\t\t\t<!--\t\t\t\t\t\t\t\t\t-->\t\t\t\t\t\t\t\t</div>\n\t\t\t\t\t\t\t\t\t\t\t\t\t\t\t\t\t<div class=\"text text-block show_body\">\n\t\t\t\t\t\t\t\t\t<span></span>\n\t\t\t\t\t\t\t\t</div>\n\t\t\t\t\t\t\t\t\t\t\t\t\t\t\t</div>\n\t\t\t\t\t\t\t\t\t\t\t\t\t\t\t\t\t\t\t\t</a>\n\t\t\t\t\t\t\t\t\t\t\t</span>\n\t\t\t\t</div>\n\t\t\t</div>","link":"https://festivallife.kr/concert/?q=YToxOntzOjEyOiJrZXl3b3JkX3R5cGUiO3M6MzoiYWxsIjt9&bmode=view&idx=17625685&t=board","retrieved":1705475903959,"image":"https://cdn.imweb.me/thumbnail/20240117/1dce720885675.gif"},{"title":"공지\n\t\t\t\t\t\t\t\t\t\t\t\t\t\t\t\t\t\t\t\n\t\t\t\t\t\t\t\t\t\t\t\n\t\t\t\t\t\t\t\t\t\t\n\t\t\t\t\t\t\t\t\t\t\t\t\t\t\t\t\t\tMPMG WEEK 2024 : 78LIVE - OurR(아월)\t\t\t\t\t\t\t\t\t\t\t\t\t\t\t\t\t\t\tN","contents":"<div class=\"ma-item _post_item_wrap\" style=\"padding: 15px;\">\n\t\t\t\t<div class=\"card  _card\" style=\"  background-size: cover; background-position: 50% 50%;\">\n\t\t\t\t\t<span class=\"holder blocked\" style=\"cursor:pointer;\">\n\t\t\t\t\t\t\t\t\t\t\t\t<a class=\"post_link_wrap _fade_link\" href=\"/concert/?q=YToxOntzOjEyOiJrZXl3b3JkX3R5cGUiO3M6MzoiYWxsIjt9&amp;bmode=view&amp;idx=17625662&amp;t=board\">\n\t\t\t\t\t\t\t<div class=\"card_wrapper card-thumbnail-wrap \" style=\"background-image: url(https://cdn.imweb.me/thumbnail/20240117/70c7edc5bd25a.gif);  background-size: cover; background-position: 50% 50%;\">\n\t\t\t\t\t\t\t\t<div class=\"card-head _card_head _img_wrap\" style=\"height: 387px;\">\n\t\t\t\t\t\t\t\t\t<span>\n\t\t\t\t\t\t\t\t\t\t\t\t\t\t\t\t\t\t\t</span>\n\t\t\t\t\t\t\t\t</div>\n\t\t\t\t\t\t\t</div>\n\t\t\t\t\t\t\t<div class=\"card-body _card_body list-group\">\n\t\t\t\t\t\t\t\t<div class=\"title title-block\">\n\t\t\t\t\t\t\t\t\t<em class=\"notice-block\" style=\"display: none\">공지</em>\n\t\t\t\t\t\t\t\t\t\t\t\t\t\t\t\t\t\t\t<span>\n\t\t\t\t\t\t\t\t\t\t\t<em style=\"padding-right:5px;color:;display: none\"></em>\n\t\t\t\t\t\t\t\t\t\t</span>\n\t\t\t\t\t\t\t\t\t\t\t\t\t\t\t\t\t\tMPMG WEEK 2024 : 78LIVE - OurR(아월)\t\t\t\t\t\t\t\t\t\t\t\t\t\t\t\t\t\t\t<span class=\"icons\"><em class=\"addon-badge\">N</em></span>\n\t\t\t\t\t\t\t\t\t<!--\t\t\t\t\t\t\t\t\t--><!--\t\t\t\t\t\t\t\t\t\t<span class=\"icons text-20 \"><i aria-hidden=\"true\" class=\"icon-picture\"></i></span>-->\n\t\t\t\t\t\t\t\t\t<!--\t\t\t\t\t\t\t\t\t--><!--\t\t\t\t\t\t\t\t\t--><!--\t\t\t\t\t\t\t\t\t\t<span class=\"icons text-20\"><i aria-hidden=\"true\" class=\"icon-folder\"></i></span>-->\n\t\t\t\t\t\t\t\t\t<!--\t\t\t\t\t\t\t\t\t--><!--\t\t\t\t\t\t\t\t\t--><!--\t\t\t\t\t\t\t\t\t\t<span class=\"icons text-20\"><i aria-hidden=\"true\" class=\"icon-camrecorder\"></i></span>-->\n\t\t\t\t\t\t\t\t\t<!--\t\t\t\t\t\t\t\t\t-->\t\t\t\t\t\t\t\t</div>\n\t\t\t\t\t\t\t\t\t\t\t\t\t\t\t\t\t<div class=\"text text-block show_body\">\n\t\t\t\t\t\t\t\t\t<span></span>\n\t\t\t\t\t\t\t\t</div>\n\t\t\t\t\t\t\t\t\t\t\t\t\t\t\t</div>\n\t\t\t\t\t\t\t\t\t\t\t\t\t\t\t\t\t\t\t\t</a>\n\t\t\t\t\t\t\t\t\t\t\t</span>\n\t\t\t\t</div>\n\t\t\t</div>","link":"https://festivallife.kr/concert/?q=YToxOntzOjEyOiJrZXl3b3JkX3R5cGUiO3M6MzoiYWxsIjt9&bmode=view&idx=17625662&t=board","retrieved":1705475903960,"image":"https://cdn.imweb.me/thumbnail/20240117/70c7edc5bd25a.gif"},{"title":"공지\n\t\t\t\t\t\t\t\t\t\t\t\t\t\t\t\t\t\t\t\n\t\t\t\t\t\t\t\t\t\t\t\n\t\t\t\t\t\t\t\t\t\t\n\t\t\t\t\t\t\t\t\t\t\t\t\t\t\t\t\t\t78LIVE - 이희상\t\t\t\t\t\t\t\t\t\t\t\t\t\t\t\t\t\t\tN","contents":"<div class=\"ma-item _post_item_wrap\" style=\"padding: 15px;\">\n\t\t\t\t<div class=\"card  _card\" style=\"  background-size: cover; background-position: 50% 50%;\">\n\t\t\t\t\t<span class=\"holder blocked\" style=\"cursor:pointer;\">\n\t\t\t\t\t\t\t\t\t\t\t\t<a class=\"post_link_wrap _fade_link\" href=\"/concert/?q=YToxOntzOjEyOiJrZXl3b3JkX3R5cGUiO3M6MzoiYWxsIjt9&amp;bmode=view&amp;idx=17625646&amp;t=board\">\n\t\t\t\t\t\t\t<div class=\"card_wrapper card-thumbnail-wrap \" style=\"background-image: url(https://cdn.imweb.me/thumbnail/20240117/b06d1abaa9bd6.gif);  background-size: cover; background-position: 50% 50%;\">\n\t\t\t\t\t\t\t\t<div class=\"card-head _card_head _img_wrap\" style=\"height: 387px;\">\n\t\t\t\t\t\t\t\t\t<span>\n\t\t\t\t\t\t\t\t\t\t\t\t\t\t\t\t\t\t\t</span>\n\t\t\t\t\t\t\t\t</div>\n\t\t\t\t\t\t\t</div>\n\t\t\t\t\t\t\t<div class=\"card-body _card_body list-group\">\n\t\t\t\t\t\t\t\t<div class=\"title title-block\">\n\t\t\t\t\t\t\t\t\t<em class=\"notice-block\" style=\"display: none\">공지</em>\n\t\t\t\t\t\t\t\t\t\t\t\t\t\t\t\t\t\t\t<span>\n\t\t\t\t\t\t\t\t\t\t\t<em style=\"padding-right:5px;color:;display: none\"></em>\n\t\t\t\t\t\t\t\t\t\t</span>\n\t\t\t\t\t\t\t\t\t\t\t\t\t\t\t\t\t\t78LIVE - 이희상\t\t\t\t\t\t\t\t\t\t\t\t\t\t\t\t\t\t\t<span class=\"icons\"><em class=\"addon-badge\">N</em></span>\n\t\t\t\t\t\t\t\t\t<!--\t\t\t\t\t\t\t\t\t--><!--\t\t\t\t\t\t\t\t\t\t<span class=\"icons text-20 \"><i aria-hidden=\"true\" class=\"icon-picture\"></i></span>-->\n\t\t\t\t\t\t\t\t\t<!--\t\t\t\t\t\t\t\t\t--><!--\t\t\t\t\t\t\t\t\t--><!--\t\t\t\t\t\t\t\t\t\t<span class=\"icons text-20\"><i aria-hidden=\"true\" class=\"icon-folder\"></i></span>-->\n\t\t\t\t\t\t\t\t\t<!--\t\t\t\t\t\t\t\t\t--><!--\t\t\t\t\t\t\t\t\t--><!--\t\t\t\t\t\t\t\t\t\t<span class=\"icons text-20\"><i aria-hidden=\"true\" class=\"icon-camrecorder\"></i></span>-->\n\t\t\t\t\t\t\t\t\t<!--\t\t\t\t\t\t\t\t\t-->\t\t\t\t\t\t\t\t</div>\n\t\t\t\t\t\t\t\t\t\t\t\t\t\t\t\t\t<div class=\"text text-block show_body\">\n\t\t\t\t\t\t\t\t\t<span></span>\n\t\t\t\t\t\t\t\t</div>\n\t\t\t\t\t\t\t\t\t\t\t\t\t\t\t</div>\n\t\t\t\t\t\t\t\t\t\t\t\t\t\t\t\t\t\t\t\t</a>\n\t\t\t\t\t\t\t\t\t\t\t</span>\n\t\t\t\t</div>\n\t\t\t</div>","link":"https://festivallife.kr/concert/?q=YToxOntzOjEyOiJrZXl3b3JkX3R5cGUiO3M6MzoiYWxsIjt9&bmode=view&idx=17625646&t=board","retrieved":1705475903963,"image":"https://cdn.imweb.me/thumbnail/20240117/b06d1abaa9bd6.gif"},{"title":"공지\n\t\t\t\t\t\t\t\t\t\t\t\t\t\t\t\t\t\t\t\n\t\t\t\t\t\t\t\t\t\t\t\n\t\t\t\t\t\t\t\t\t\t\n\t\t\t\t\t\t\t\t\t\t\t\t\t\t\t\t\t\tMPMG WEEK 2024 : BLUE LABEL - 권순관\t\t\t\t\t\t\t\t\t\t\t\t\t\t\t\t\t\t\tN","contents":"<div class=\"ma-item _post_item_wrap\" style=\"padding: 15px;\">\n\t\t\t\t<div class=\"card  _card\" style=\"  background-size: cover; background-position: 50% 50%;\">\n\t\t\t\t\t<span class=\"holder blocked\" style=\"cursor:pointer;\">\n\t\t\t\t\t\t\t\t\t\t\t\t<a class=\"post_link_wrap _fade_link\" href=\"/concert/?q=YToxOntzOjEyOiJrZXl3b3JkX3R5cGUiO3M6MzoiYWxsIjt9&amp;bmode=view&amp;idx=17625627&amp;t=board\">\n\t\t\t\t\t\t\t<div class=\"card_wrapper card-thumbnail-wrap \" style=\"background-image: url(https://cdn.imweb.me/thumbnail/20240117/e79d9023b75f2.gif);  background-size: cover; background-position: 50% 50%;\">\n\t\t\t\t\t\t\t\t<div class=\"card-head _card_head _img_wrap\" style=\"height: 387px;\">\n\t\t\t\t\t\t\t\t\t<span>\n\t\t\t\t\t\t\t\t\t\t\t\t\t\t\t\t\t\t\t</span>\n\t\t\t\t\t\t\t\t</div>\n\t\t\t\t\t\t\t</div>\n\t\t\t\t\t\t\t<div class=\"card-body _card_body list-group\">\n\t\t\t\t\t\t\t\t<div class=\"title title-block\">\n\t\t\t\t\t\t\t\t\t<em class=\"notice-block\" style=\"display: none\">공지</em>\n\t\t\t\t\t\t\t\t\t\t\t\t\t\t\t\t\t\t\t<span>\n\t\t\t\t\t\t\t\t\t\t\t<em style=\"padding-right:5px;color:;display: none\"></em>\n\t\t\t\t\t\t\t\t\t\t</span>\n\t\t\t\t\t\t\t\t\t\t\t\t\t\t\t\t\t\tMPMG WEEK 2024 : BLUE LABEL - 권순관\t\t\t\t\t\t\t\t\t\t\t\t\t\t\t\t\t\t\t<span class=\"icons\"><em class=\"addon-badge\">N</em></span>\n\t\t\t\t\t\t\t\t\t<!--\t\t\t\t\t\t\t\t\t--><!--\t\t\t\t\t\t\t\t\t\t<span class=\"icons text-20 \"><i aria-hidden=\"true\" class=\"icon-picture\"></i></span>-->\n\t\t\t\t\t\t\t\t\t<!--\t\t\t\t\t\t\t\t\t--><!--\t\t\t\t\t\t\t\t\t--><!--\t\t\t\t\t\t\t\t\t\t<span class=\"icons text-20\"><i aria-hidden=\"true\" class=\"icon-folder\"></i></span>-->\n\t\t\t\t\t\t\t\t\t<!--\t\t\t\t\t\t\t\t\t--><!--\t\t\t\t\t\t\t\t\t--><!--\t\t\t\t\t\t\t\t\t\t<span class=\"icons text-20\"><i aria-hidden=\"true\" class=\"icon-camrecorder\"></i></span>-->\n\t\t\t\t\t\t\t\t\t<!--\t\t\t\t\t\t\t\t\t-->\t\t\t\t\t\t\t\t</div>\n\t\t\t\t\t\t\t\t\t\t\t\t\t\t\t\t\t<div class=\"text text-block show_body\">\n\t\t\t\t\t\t\t\t\t<span></span>\n\t\t\t\t\t\t\t\t</div>\n\t\t\t\t\t\t\t\t\t\t\t\t\t\t\t</div>\n\t\t\t\t\t\t\t\t\t\t\t\t\t\t\t\t\t\t\t\t</a>\n\t\t\t\t\t\t\t\t\t\t\t</span>\n\t\t\t\t</div>\n\t\t\t</div>","link":"https://festivallife.kr/concert/?q=YToxOntzOjEyOiJrZXl3b3JkX3R5cGUiO3M6MzoiYWxsIjt9&bmode=view&idx=17625627&t=board","retrieved":1705475903964,"image":"https://cdn.imweb.me/thumbnail/20240117/e79d9023b75f2.gif"},{"title":"공지\n\t\t\t\t\t\t\t\t\t\t\t\t\t\t\t\t\t\t\t\n\t\t\t\t\t\t\t\t\t\t\t\n\t\t\t\t\t\t\t\t\t\t\n\t\t\t\t\t\t\t\t\t\t\t\t\t\t\t\t\t\tMPMG WEEK 2024 : BLUE LABEL - 유다빈밴드\t\t\t\t\t\t\t\t\t\t\t\t\t\t\t\t\t\t\tN","contents":"<div class=\"ma-item _post_item_wrap\" style=\"padding: 15px;\">\n\t\t\t\t<div class=\"card  _card\" style=\"  background-size: cover; background-position: 50% 50%;\">\n\t\t\t\t\t<span class=\"holder blocked\" style=\"cursor:pointer;\">\n\t\t\t\t\t\t\t\t\t\t\t\t<a class=\"post_link_wrap _fade_link\" href=\"/concert/?q=YToxOntzOjEyOiJrZXl3b3JkX3R5cGUiO3M6MzoiYWxsIjt9&amp;bmode=view&amp;idx=17625612&amp;t=board\">\n\t\t\t\t\t\t\t<div class=\"card_wrapper card-thumbnail-wrap \" style=\"background-image: url(https://cdn.imweb.me/thumbnail/20240117/8925c09d3e640.gif);  background-size: cover; background-position: 50% 50%;\">\n\t\t\t\t\t\t\t\t<div class=\"card-head _card_head _img_wrap\" style=\"height: 387px;\">\n\t\t\t\t\t\t\t\t\t<span>\n\t\t\t\t\t\t\t\t\t\t\t\t\t\t\t\t\t\t\t</span>\n\t\t\t\t\t\t\t\t</div>\n\t\t\t\t\t\t\t</div>\n\t\t\t\t\t\t\t<div class=\"card-body _card_body list-group\">\n\t\t\t\t\t\t\t\t<div class=\"title title-block\">\n\t\t\t\t\t\t\t\t\t<em class=\"notice-block\" style=\"display: none\">공지</em>\n\t\t\t\t\t\t\t\t\t\t\t\t\t\t\t\t\t\t\t<span>\n\t\t\t\t\t\t\t\t\t\t\t<em style=\"padding-right:5px;color:;display: none\"></em>\n\t\t\t\t\t\t\t\t\t\t</span>\n\t\t\t\t\t\t\t\t\t\t\t\t\t\t\t\t\t\tMPMG WEEK 2024 : BLUE LABEL - 유다빈밴드\t\t\t\t\t\t\t\t\t\t\t\t\t\t\t\t\t\t\t<span class=\"icons\"><em class=\"addon-badge\">N</em></span>\n\t\t\t\t\t\t\t\t\t<!--\t\t\t\t\t\t\t\t\t--><!--\t\t\t\t\t\t\t\t\t\t<span class=\"icons text-20 \"><i aria-hidden=\"true\" class=\"icon-picture\"></i></span>-->\n\t\t\t\t\t\t\t\t\t<!--\t\t\t\t\t\t\t\t\t--><!--\t\t\t\t\t\t\t\t\t--><!--\t\t\t\t\t\t\t\t\t\t<span class=\"icons text-20\"><i aria-hidden=\"true\" class=\"icon-folder\"></i></span>-->\n\t\t\t\t\t\t\t\t\t<!--\t\t\t\t\t\t\t\t\t--><!--\t\t\t\t\t\t\t\t\t--><!--\t\t\t\t\t\t\t\t\t\t<span class=\"icons text-20\"><i aria-hidden=\"true\" class=\"icon-camrecorder\"></i></span>-->\n\t\t\t\t\t\t\t\t\t<!--\t\t\t\t\t\t\t\t\t-->\t\t\t\t\t\t\t\t</div>\n\t\t\t\t\t\t\t\t\t\t\t\t\t\t\t\t\t<div class=\"text text-block show_body\">\n\t\t\t\t\t\t\t\t\t<span></span>\n\t\t\t\t\t\t\t\t</div>\n\t\t\t\t\t\t\t\t\t\t\t\t\t\t\t</div>\n\t\t\t\t\t\t\t\t\t\t\t\t\t\t\t\t\t\t\t\t</a>\n\t\t\t\t\t\t\t\t\t\t\t</span>\n\t\t\t\t</div>\n\t\t\t</div>","link":"https://festivallife.kr/concert/?q=YToxOntzOjEyOiJrZXl3b3JkX3R5cGUiO3M6MzoiYWxsIjt9&bmode=view&idx=17625612&t=board","retrieved":1705475903965,"image":"https://cdn.imweb.me/thumbnail/20240117/8925c09d3e640.gif"},{"title":"공지\n\t\t\t\t\t\t\t\t\t\t\t\t\t\t\t\t\t\t\t\n\t\t\t\t\t\t\t\t\t\t\t\n\t\t\t\t\t\t\t\t\t\t\n\t\t\t\t\t\t\t\t\t\t\t\t\t\t\t\t\t\tMPMG WEEK 2024 : BLUE LABEL - 소란\t\t\t\t\t\t\t\t\t\t\t\t\t\t\t\t\t\t\tN","contents":"<div class=\"ma-item _post_item_wrap\" style=\"padding: 15px;\">\n\t\t\t\t<div class=\"card  _card\" style=\"  background-size: cover; background-position: 50% 50%;\">\n\t\t\t\t\t<span class=\"holder blocked\" style=\"cursor:pointer;\">\n\t\t\t\t\t\t\t\t\t\t\t\t<a class=\"post_link_wrap _fade_link\" href=\"/concert/?q=YToxOntzOjEyOiJrZXl3b3JkX3R5cGUiO3M6MzoiYWxsIjt9&amp;bmode=view&amp;idx=17625597&amp;t=board\">\n\t\t\t\t\t\t\t<div class=\"card_wrapper card-thumbnail-wrap \" style=\"background-image: url(https://cdn.imweb.me/thumbnail/20240117/8a588b7fd3e6d.gif);  background-size: cover; background-position: 50% 50%;\">\n\t\t\t\t\t\t\t\t<div class=\"card-head _card_head _img_wrap\" style=\"height: 387px;\">\n\t\t\t\t\t\t\t\t\t<span>\n\t\t\t\t\t\t\t\t\t\t\t\t\t\t\t\t\t\t\t</span>\n\t\t\t\t\t\t\t\t</div>\n\t\t\t\t\t\t\t</div>\n\t\t\t\t\t\t\t<div class=\"card-body _card_body list-group\">\n\t\t\t\t\t\t\t\t<div class=\"title title-block\">\n\t\t\t\t\t\t\t\t\t<em class=\"notice-block\" style=\"display: none\">공지</em>\n\t\t\t\t\t\t\t\t\t\t\t\t\t\t\t\t\t\t\t<span>\n\t\t\t\t\t\t\t\t\t\t\t<em style=\"padding-right:5px;color:;display: none\"></em>\n\t\t\t\t\t\t\t\t\t\t</span>\n\t\t\t\t\t\t\t\t\t\t\t\t\t\t\t\t\t\tMPMG WEEK 2024 : BLUE LABEL - 소란\t\t\t\t\t\t\t\t\t\t\t\t\t\t\t\t\t\t\t<span class=\"icons\"><em class=\"addon-badge\">N</em></span>\n\t\t\t\t\t\t\t\t\t<!--\t\t\t\t\t\t\t\t\t--><!--\t\t\t\t\t\t\t\t\t\t<span class=\"icons text-20 \"><i aria-hidden=\"true\" class=\"icon-picture\"></i></span>-->\n\t\t\t\t\t\t\t\t\t<!--\t\t\t\t\t\t\t\t\t--><!--\t\t\t\t\t\t\t\t\t--><!--\t\t\t\t\t\t\t\t\t\t<span class=\"icons text-20\"><i aria-hidden=\"true\" class=\"icon-folder\"></i></span>-->\n\t\t\t\t\t\t\t\t\t<!--\t\t\t\t\t\t\t\t\t--><!--\t\t\t\t\t\t\t\t\t--><!--\t\t\t\t\t\t\t\t\t\t<span class=\"icons text-20\"><i aria-hidden=\"true\" class=\"icon-camrecorder\"></i></span>-->\n\t\t\t\t\t\t\t\t\t<!--\t\t\t\t\t\t\t\t\t-->\t\t\t\t\t\t\t\t</div>\n\t\t\t\t\t\t\t\t\t\t\t\t\t\t\t\t\t<div class=\"text text-block show_body\">\n\t\t\t\t\t\t\t\t\t<span></span>\n\t\t\t\t\t\t\t\t</div>\n\t\t\t\t\t\t\t\t\t\t\t\t\t\t\t</div>\n\t\t\t\t\t\t\t\t\t\t\t\t\t\t\t\t\t\t\t\t</a>\n\t\t\t\t\t\t\t\t\t\t\t</span>\n\t\t\t\t</div>\n\t\t\t</div>","link":"https://festivallife.kr/concert/?q=YToxOntzOjEyOiJrZXl3b3JkX3R5cGUiO3M6MzoiYWxsIjt9&bmode=view&idx=17625597&t=board","retrieved":1705475903967,"image":"https://cdn.imweb.me/thumbnail/20240117/8a588b7fd3e6d.gif"},{"title":"공지\n\t\t\t\t\t\t\t\t\t\t\t\t\t\t\t\t\t\t\t\n\t\t\t\t\t\t\t\t\t\t\t\n\t\t\t\t\t\t\t\t\t\t\n\t\t\t\t\t\t\t\t\t\t\t\t\t\t\t\t\t\tMPMG WEEK 2024 : BLUE LABEL - Lacuna (라쿠나)\t\t\t\t\t\t\t\t\t\t\t\t\t\t\t\t\t\t\tN","contents":"<div class=\"ma-item _post_item_wrap\" style=\"padding: 15px;\">\n\t\t\t\t<div class=\"card  _card\" style=\"  background-size: cover; background-position: 50% 50%;\">\n\t\t\t\t\t<span class=\"holder blocked\" style=\"cursor:pointer;\">\n\t\t\t\t\t\t\t\t\t\t\t\t<a class=\"post_link_wrap _fade_link\" href=\"/concert/?q=YToxOntzOjEyOiJrZXl3b3JkX3R5cGUiO3M6MzoiYWxsIjt9&amp;bmode=view&amp;idx=17625579&amp;t=board\">\n\t\t\t\t\t\t\t<div class=\"card_wrapper card-thumbnail-wrap \" style=\"background-image: url(https://cdn.imweb.me/thumbnail/20240117/87cfcdc210c49.gif);  background-size: cover; background-position: 50% 50%;\">\n\t\t\t\t\t\t\t\t<div class=\"card-head _card_head _img_wrap\" style=\"height: 387px;\">\n\t\t\t\t\t\t\t\t\t<span>\n\t\t\t\t\t\t\t\t\t\t\t\t\t\t\t\t\t\t\t</span>\n\t\t\t\t\t\t\t\t</div>\n\t\t\t\t\t\t\t</div>\n\t\t\t\t\t\t\t<div class=\"card-body _card_body list-group\">\n\t\t\t\t\t\t\t\t<div class=\"title title-block\">\n\t\t\t\t\t\t\t\t\t<em class=\"notice-block\" style=\"display: none\">공지</em>\n\t\t\t\t\t\t\t\t\t\t\t\t\t\t\t\t\t\t\t<span>\n\t\t\t\t\t\t\t\t\t\t\t<em style=\"padding-right:5px;color:;display: none\"></em>\n\t\t\t\t\t\t\t\t\t\t</span>\n\t\t\t\t\t\t\t\t\t\t\t\t\t\t\t\t\t\tMPMG WEEK 2024 : BLUE LABEL - Lacuna (라쿠나)\t\t\t\t\t\t\t\t\t\t\t\t\t\t\t\t\t\t\t<span class=\"icons\"><em class=\"addon-badge\">N</em></span>\n\t\t\t\t\t\t\t\t\t<!--\t\t\t\t\t\t\t\t\t--><!--\t\t\t\t\t\t\t\t\t\t<span class=\"icons text-20 \"><i aria-hidden=\"true\" class=\"icon-picture\"></i></span>-->\n\t\t\t\t\t\t\t\t\t<!--\t\t\t\t\t\t\t\t\t--><!--\t\t\t\t\t\t\t\t\t--><!--\t\t\t\t\t\t\t\t\t\t<span class=\"icons text-20\"><i aria-hidden=\"true\" class=\"icon-folder\"></i></span>-->\n\t\t\t\t\t\t\t\t\t<!--\t\t\t\t\t\t\t\t\t--><!--\t\t\t\t\t\t\t\t\t--><!--\t\t\t\t\t\t\t\t\t\t<span class=\"icons text-20\"><i aria-hidden=\"true\" class=\"icon-camrecorder\"></i></span>-->\n\t\t\t\t\t\t\t\t\t<!--\t\t\t\t\t\t\t\t\t-->\t\t\t\t\t\t\t\t</div>\n\t\t\t\t\t\t\t\t\t\t\t\t\t\t\t\t\t<div class=\"text text-block show_body\">\n\t\t\t\t\t\t\t\t\t<span></span>\n\t\t\t\t\t\t\t\t</div>\n\t\t\t\t\t\t\t\t\t\t\t\t\t\t\t</div>\n\t\t\t\t\t\t\t\t\t\t\t\t\t\t\t\t\t\t\t\t</a>\n\t\t\t\t\t\t\t\t\t\t\t</span>\n\t\t\t\t</div>\n\t\t\t</div>","link":"https://festivallife.kr/concert/?q=YToxOntzOjEyOiJrZXl3b3JkX3R5cGUiO3M6MzoiYWxsIjt9&bmode=view&idx=17625579&t=board","retrieved":1705475903968,"image":"https://cdn.imweb.me/thumbnail/20240117/87cfcdc210c49.gif"},{"title":"공지\n\t\t\t\t\t\t\t\t\t\t\t\t\t\t\t\t\t\t\t\n\t\t\t\t\t\t\t\t\t\t\t\n\t\t\t\t\t\t\t\t\t\t\n\t\t\t\t\t\t\t\t\t\t\t\t\t\t\t\t\t\tMPMG WEEK 2024 : BLUE LABEL - 터치드(TOUCHED)\t\t\t\t\t\t\t\t\t\t\t\t\t\t\t\t\t\t\tN","contents":"<div class=\"ma-item _post_item_wrap\" style=\"padding: 15px;\">\n\t\t\t\t<div class=\"card  _card\" style=\"  background-size: cover; background-position: 50% 50%;\">\n\t\t\t\t\t<span class=\"holder blocked\" style=\"cursor:pointer;\">\n\t\t\t\t\t\t\t\t\t\t\t\t<a class=\"post_link_wrap _fade_link\" href=\"/concert/?q=YToxOntzOjEyOiJrZXl3b3JkX3R5cGUiO3M6MzoiYWxsIjt9&amp;bmode=view&amp;idx=17625565&amp;t=board\">\n\t\t\t\t\t\t\t<div class=\"card_wrapper card-thumbnail-wrap \" style=\"background-image: url(https://cdn.imweb.me/thumbnail/20240117/ad6a14d9dcb1c.gif);  background-size: cover; background-position: 50% 50%;\">\n\t\t\t\t\t\t\t\t<div class=\"card-head _card_head _img_wrap\" style=\"height: 387px;\">\n\t\t\t\t\t\t\t\t\t<span>\n\t\t\t\t\t\t\t\t\t\t\t\t\t\t\t\t\t\t\t</span>\n\t\t\t\t\t\t\t\t</div>\n\t\t\t\t\t\t\t</div>\n\t\t\t\t\t\t\t<div class=\"card-body _card_body list-group\">\n\t\t\t\t\t\t\t\t<div class=\"title title-block\">\n\t\t\t\t\t\t\t\t\t<em class=\"notice-block\" style=\"display: none\">공지</em>\n\t\t\t\t\t\t\t\t\t\t\t\t\t\t\t\t\t\t\t<span>\n\t\t\t\t\t\t\t\t\t\t\t<em style=\"padding-right:5px;color:;display: none\"></em>\n\t\t\t\t\t\t\t\t\t\t</span>\n\t\t\t\t\t\t\t\t\t\t\t\t\t\t\t\t\t\tMPMG WEEK 2024 : BLUE LABEL - 터치드(TOUCHED)\t\t\t\t\t\t\t\t\t\t\t\t\t\t\t\t\t\t\t<span class=\"icons\"><em class=\"addon-badge\">N</em></span>\n\t\t\t\t\t\t\t\t\t<!--\t\t\t\t\t\t\t\t\t--><!--\t\t\t\t\t\t\t\t\t\t<span class=\"icons text-20 \"><i aria-hidden=\"true\" class=\"icon-picture\"></i></span>-->\n\t\t\t\t\t\t\t\t\t<!--\t\t\t\t\t\t\t\t\t--><!--\t\t\t\t\t\t\t\t\t--><!--\t\t\t\t\t\t\t\t\t\t<span class=\"icons text-20\"><i aria-hidden=\"true\" class=\"icon-folder\"></i></span>-->\n\t\t\t\t\t\t\t\t\t<!--\t\t\t\t\t\t\t\t\t--><!--\t\t\t\t\t\t\t\t\t--><!--\t\t\t\t\t\t\t\t\t\t<span class=\"icons text-20\"><i aria-hidden=\"true\" class=\"icon-camrecorder\"></i></span>-->\n\t\t\t\t\t\t\t\t\t<!--\t\t\t\t\t\t\t\t\t-->\t\t\t\t\t\t\t\t</div>\n\t\t\t\t\t\t\t\t\t\t\t\t\t\t\t\t\t<div class=\"text text-block show_body\">\n\t\t\t\t\t\t\t\t\t<span></span>\n\t\t\t\t\t\t\t\t</div>\n\t\t\t\t\t\t\t\t\t\t\t\t\t\t\t</div>\n\t\t\t\t\t\t\t\t\t\t\t\t\t\t\t\t\t\t\t\t</a>\n\t\t\t\t\t\t\t\t\t\t\t</span>\n\t\t\t\t</div>\n\t\t\t</div>","link":"https://festivallife.kr/concert/?q=YToxOntzOjEyOiJrZXl3b3JkX3R5cGUiO3M6MzoiYWxsIjt9&bmode=view&idx=17625565&t=board","retrieved":1705475903970,"image":"https://cdn.imweb.me/thumbnail/20240117/ad6a14d9dcb1c.gif"},{"title":"공지\n\t\t\t\t\t\t\t\t\t\t\t\t\t\t\t\t\t\t\t\n\t\t\t\t\t\t\t\t\t\t\t\n\t\t\t\t\t\t\t\t\t\t\n\t\t\t\t\t\t\t\t\t\t\t\t\t\t\t\t\t\tMPMG WEEK 2024 : BLUE LABEL - THE SOLUTIONS\t\t\t\t\t\t\t\t\t\t\t\t\t\t\t\t\t\t\tN","contents":"<div class=\"ma-item _post_item_wrap\" style=\"padding: 15px;\">\n\t\t\t\t<div class=\"card  _card\" style=\"  background-size: cover; background-position: 50% 50%;\">\n\t\t\t\t\t<span class=\"holder blocked\" style=\"cursor:pointer;\">\n\t\t\t\t\t\t\t\t\t\t\t\t<a class=\"post_link_wrap _fade_link\" href=\"/concert/?q=YToxOntzOjEyOiJrZXl3b3JkX3R5cGUiO3M6MzoiYWxsIjt9&amp;bmode=view&amp;idx=17625548&amp;t=board\">\n\t\t\t\t\t\t\t<div class=\"card_wrapper card-thumbnail-wrap \" style=\"background-image: url(https://cdn.imweb.me/thumbnail/20240117/5d824a022ca0d.gif);  background-size: cover; background-position: 50% 50%;\">\n\t\t\t\t\t\t\t\t<div class=\"card-head _card_head _img_wrap\" style=\"height: 387px;\">\n\t\t\t\t\t\t\t\t\t<span>\n\t\t\t\t\t\t\t\t\t\t\t\t\t\t\t\t\t\t\t</span>\n\t\t\t\t\t\t\t\t</div>\n\t\t\t\t\t\t\t</div>\n\t\t\t\t\t\t\t<div class=\"card-body _card_body list-group\">\n\t\t\t\t\t\t\t\t<div class=\"title title-block\">\n\t\t\t\t\t\t\t\t\t<em class=\"notice-block\" style=\"display: none\">공지</em>\n\t\t\t\t\t\t\t\t\t\t\t\t\t\t\t\t\t\t\t<span>\n\t\t\t\t\t\t\t\t\t\t\t<em style=\"padding-right:5px;color:;display: none\"></em>\n\t\t\t\t\t\t\t\t\t\t</span>\n\t\t\t\t\t\t\t\t\t\t\t\t\t\t\t\t\t\tMPMG WEEK 2024 : BLUE LABEL - THE SOLUTIONS\t\t\t\t\t\t\t\t\t\t\t\t\t\t\t\t\t\t\t<span class=\"icons\"><em class=\"addon-badge\">N</em></span>\n\t\t\t\t\t\t\t\t\t<!--\t\t\t\t\t\t\t\t\t--><!--\t\t\t\t\t\t\t\t\t\t<span class=\"icons text-20 \"><i aria-hidden=\"true\" class=\"icon-picture\"></i></span>-->\n\t\t\t\t\t\t\t\t\t<!--\t\t\t\t\t\t\t\t\t--><!--\t\t\t\t\t\t\t\t\t--><!--\t\t\t\t\t\t\t\t\t\t<span class=\"icons text-20\"><i aria-hidden=\"true\" class=\"icon-folder\"></i></span>-->\n\t\t\t\t\t\t\t\t\t<!--\t\t\t\t\t\t\t\t\t--><!--\t\t\t\t\t\t\t\t\t--><!--\t\t\t\t\t\t\t\t\t\t<span class=\"icons text-20\"><i aria-hidden=\"true\" class=\"icon-camrecorder\"></i></span>-->\n\t\t\t\t\t\t\t\t\t<!--\t\t\t\t\t\t\t\t\t-->\t\t\t\t\t\t\t\t</div>\n\t\t\t\t\t\t\t\t\t\t\t\t\t\t\t\t\t<div class=\"text text-block show_body\">\n\t\t\t\t\t\t\t\t\t<span></span>\n\t\t\t\t\t\t\t\t</div>\n\t\t\t\t\t\t\t\t\t\t\t\t\t\t\t</div>\n\t\t\t\t\t\t\t\t\t\t\t\t\t\t\t\t\t\t\t\t</a>\n\t\t\t\t\t\t\t\t\t\t\t</span>\n\t\t\t\t</div>\n\t\t\t</div>","link":"https://festivallife.kr/concert/?q=YToxOntzOjEyOiJrZXl3b3JkX3R5cGUiO3M6MzoiYWxsIjt9&bmode=view&idx=17625548&t=board","retrieved":1705475903971,"image":"https://cdn.imweb.me/thumbnail/20240117/5d824a022ca0d.gif"},{"title":"공지\n\t\t\t\t\t\t\t\t\t\t\t\t\t\t\t\t\t\t\t\n\t\t\t\t\t\t\t\t\t\t\t\n\t\t\t\t\t\t\t\t\t\t\n\t\t\t\t\t\t\t\t\t\t\t\t\t\t\t\t\t\tMPMG WEEK 2024 : BLUE LABEL - SURL(설)\t\t\t\t\t\t\t\t\t\t\t\t\t\t\t\t\t\t\tN","contents":"<div class=\"ma-item _post_item_wrap\" style=\"padding: 15px;\">\n\t\t\t\t<div class=\"card  _card\" style=\"  background-size: cover; background-position: 50% 50%;\">\n\t\t\t\t\t<span class=\"holder blocked\" style=\"cursor:pointer;\">\n\t\t\t\t\t\t\t\t\t\t\t\t<a class=\"post_link_wrap _fade_link\" href=\"/concert/?q=YToxOntzOjEyOiJrZXl3b3JkX3R5cGUiO3M6MzoiYWxsIjt9&amp;bmode=view&amp;idx=17625515&amp;t=board\">\n\t\t\t\t\t\t\t<div class=\"card_wrapper card-thumbnail-wrap \" style=\"background-image: url(https://cdn.imweb.me/thumbnail/20240117/9f6fbd5568b20.gif);  background-size: cover; background-position: 50% 50%;\">\n\t\t\t\t\t\t\t\t<div class=\"card-head _card_head _img_wrap\" style=\"height: 387px;\">\n\t\t\t\t\t\t\t\t\t<span>\n\t\t\t\t\t\t\t\t\t\t\t\t\t\t\t\t\t\t\t</span>\n\t\t\t\t\t\t\t\t</div>\n\t\t\t\t\t\t\t</div>\n\t\t\t\t\t\t\t<div class=\"card-body _card_body list-group\">\n\t\t\t\t\t\t\t\t<div class=\"title title-block\">\n\t\t\t\t\t\t\t\t\t<em class=\"notice-block\" style=\"display: none\">공지</em>\n\t\t\t\t\t\t\t\t\t\t\t\t\t\t\t\t\t\t\t<span>\n\t\t\t\t\t\t\t\t\t\t\t<em style=\"padding-right:5px;color:;display: none\"></em>\n\t\t\t\t\t\t\t\t\t\t</span>\n\t\t\t\t\t\t\t\t\t\t\t\t\t\t\t\t\t\tMPMG WEEK 2024 : BLUE LABEL - SURL(설)\t\t\t\t\t\t\t\t\t\t\t\t\t\t\t\t\t\t\t<span class=\"icons\"><em class=\"addon-badge\">N</em></span>\n\t\t\t\t\t\t\t\t\t<!--\t\t\t\t\t\t\t\t\t--><!--\t\t\t\t\t\t\t\t\t\t<span class=\"icons text-20 \"><i aria-hidden=\"true\" class=\"icon-picture\"></i></span>-->\n\t\t\t\t\t\t\t\t\t<!--\t\t\t\t\t\t\t\t\t--><!--\t\t\t\t\t\t\t\t\t--><!--\t\t\t\t\t\t\t\t\t\t<span class=\"icons text-20\"><i aria-hidden=\"true\" class=\"icon-folder\"></i></span>-->\n\t\t\t\t\t\t\t\t\t<!--\t\t\t\t\t\t\t\t\t--><!--\t\t\t\t\t\t\t\t\t--><!--\t\t\t\t\t\t\t\t\t\t<span class=\"icons text-20\"><i aria-hidden=\"true\" class=\"icon-camrecorder\"></i></span>-->\n\t\t\t\t\t\t\t\t\t<!--\t\t\t\t\t\t\t\t\t-->\t\t\t\t\t\t\t\t</div>\n\t\t\t\t\t\t\t\t\t\t\t\t\t\t\t\t\t<div class=\"text text-block show_body\">\n\t\t\t\t\t\t\t\t\t<span></span>\n\t\t\t\t\t\t\t\t</div>\n\t\t\t\t\t\t\t\t\t\t\t\t\t\t\t</div>\n\t\t\t\t\t\t\t\t\t\t\t\t\t\t\t\t\t\t\t\t</a>\n\t\t\t\t\t\t\t\t\t\t\t</span>\n\t\t\t\t</div>\n\t\t\t</div>","link":"https://festivallife.kr/concert/?q=YToxOntzOjEyOiJrZXl3b3JkX3R5cGUiO3M6MzoiYWxsIjt9&bmode=view&idx=17625515&t=board","retrieved":1705475903973,"image":"https://cdn.imweb.me/thumbnail/20240117/9f6fbd5568b20.gif"},{"title":"공지\n\t\t\t\t\t\t\t\t\t\t\t\t\t\t\t\t\t\t\t\n\t\t\t\t\t\t\t\t\t\t\t\n\t\t\t\t\t\t\t\t\t\t\n\t\t\t\t\t\t\t\t\t\t\t\t\t\t\t\t\t\tMPMG WEEK 2024 : BLUE LABEL - 쏜애플\t\t\t\t\t\t\t\t\t\t\t\t\t\t\t\t\t\t\tN","contents":"<div class=\"ma-item _post_item_wrap\" style=\"padding: 15px;\">\n\t\t\t\t<div class=\"card  _card\" style=\"  background-size: cover; background-position: 50% 50%;\">\n\t\t\t\t\t<span class=\"holder blocked\" style=\"cursor:pointer;\">\n\t\t\t\t\t\t\t\t\t\t\t\t<a class=\"post_link_wrap _fade_link\" href=\"/concert/?q=YToxOntzOjEyOiJrZXl3b3JkX3R5cGUiO3M6MzoiYWxsIjt9&amp;bmode=view&amp;idx=17625500&amp;t=board\">\n\t\t\t\t\t\t\t<div class=\"card_wrapper card-thumbnail-wrap \" style=\"background-image: url(https://cdn.imweb.me/thumbnail/20240117/b5fad4fdab653.gif);  background-size: cover; background-position: 50% 50%;\">\n\t\t\t\t\t\t\t\t<div class=\"card-head _card_head _img_wrap\" style=\"height: 387px;\">\n\t\t\t\t\t\t\t\t\t<span>\n\t\t\t\t\t\t\t\t\t\t\t\t\t\t\t\t\t\t\t</span>\n\t\t\t\t\t\t\t\t</div>\n\t\t\t\t\t\t\t</div>\n\t\t\t\t\t\t\t<div class=\"card-body _card_body list-group\">\n\t\t\t\t\t\t\t\t<div class=\"title title-block\">\n\t\t\t\t\t\t\t\t\t<em class=\"notice-block\" style=\"display: none\">공지</em>\n\t\t\t\t\t\t\t\t\t\t\t\t\t\t\t\t\t\t\t<span>\n\t\t\t\t\t\t\t\t\t\t\t<em style=\"padding-right:5px;color:;display: none\"></em>\n\t\t\t\t\t\t\t\t\t\t</span>\n\t\t\t\t\t\t\t\t\t\t\t\t\t\t\t\t\t\tMPMG WEEK 2024 : BLUE LABEL - 쏜애플\t\t\t\t\t\t\t\t\t\t\t\t\t\t\t\t\t\t\t<span class=\"icons\"><em class=\"addon-badge\">N</em></span>\n\t\t\t\t\t\t\t\t\t<!--\t\t\t\t\t\t\t\t\t--><!--\t\t\t\t\t\t\t\t\t\t<span class=\"icons text-20 \"><i aria-hidden=\"true\" class=\"icon-picture\"></i></span>-->\n\t\t\t\t\t\t\t\t\t<!--\t\t\t\t\t\t\t\t\t--><!--\t\t\t\t\t\t\t\t\t--><!--\t\t\t\t\t\t\t\t\t\t<span class=\"icons text-20\"><i aria-hidden=\"true\" class=\"icon-folder\"></i></span>-->\n\t\t\t\t\t\t\t\t\t<!--\t\t\t\t\t\t\t\t\t--><!--\t\t\t\t\t\t\t\t\t--><!--\t\t\t\t\t\t\t\t\t\t<span class=\"icons text-20\"><i aria-hidden=\"true\" class=\"icon-camrecorder\"></i></span>-->\n\t\t\t\t\t\t\t\t\t<!--\t\t\t\t\t\t\t\t\t-->\t\t\t\t\t\t\t\t</div>\n\t\t\t\t\t\t\t\t\t\t\t\t\t\t\t\t\t<div class=\"text text-block show_body\">\n\t\t\t\t\t\t\t\t\t<span></span>\n\t\t\t\t\t\t\t\t</div>\n\t\t\t\t\t\t\t\t\t\t\t\t\t\t\t</div>\n\t\t\t\t\t\t\t\t\t\t\t\t\t\t\t\t\t\t\t\t</a>\n\t\t\t\t\t\t\t\t\t\t\t</span>\n\t\t\t\t</div>\n\t\t\t</div>","link":"https://festivallife.kr/concert/?q=YToxOntzOjEyOiJrZXl3b3JkX3R5cGUiO3M6MzoiYWxsIjt9&bmode=view&idx=17625500&t=board","retrieved":1705475903975,"image":"https://cdn.imweb.me/thumbnail/20240117/b5fad4fdab653.gif"},{"title":"공지\n\t\t\t\t\t\t\t\t\t\t\t\t\t\t\t\t\t\t\t\n\t\t\t\t\t\t\t\t\t\t\t\n\t\t\t\t\t\t\t\t\t\t\n\t\t\t\t\t\t\t\t\t\t\t\t\t\t\t\t\t\t친구가 되자 vol．3：브로콜리너마저 x 전기뱀장어","contents":"<div class=\"ma-item _post_item_wrap\" style=\"padding: 15px;\">\n\t\t\t\t<div class=\"card  _card\" style=\"  background-size: cover; background-position: 50% 50%;\">\n\t\t\t\t\t<span class=\"holder blocked\" style=\"cursor:pointer;\">\n\t\t\t\t\t\t\t\t\t\t\t\t<a class=\"post_link_wrap _fade_link\" href=\"/concert/?q=YToxOntzOjEyOiJrZXl3b3JkX3R5cGUiO3M6MzoiYWxsIjt9&amp;bmode=view&amp;idx=17548812&amp;t=board\">\n\t\t\t\t\t\t\t<div class=\"card_wrapper card-thumbnail-wrap \" style=\"background-image: url(https://cdn.imweb.me/thumbnail/20240110/3fe482ed6d8c3.jpg);  background-size: cover; background-position: 50% 50%;\">\n\t\t\t\t\t\t\t\t<div class=\"card-head _card_head _img_wrap\" style=\"height: 387px;\">\n\t\t\t\t\t\t\t\t\t<span>\n\t\t\t\t\t\t\t\t\t\t\t\t\t\t\t\t\t\t\t</span>\n\t\t\t\t\t\t\t\t</div>\n\t\t\t\t\t\t\t</div>\n\t\t\t\t\t\t\t<div class=\"card-body _card_body list-group\">\n\t\t\t\t\t\t\t\t<div class=\"title title-block\">\n\t\t\t\t\t\t\t\t\t<em class=\"notice-block\" style=\"display: none\">공지</em>\n\t\t\t\t\t\t\t\t\t\t\t\t\t\t\t\t\t\t\t<span>\n\t\t\t\t\t\t\t\t\t\t\t<em style=\"padding-right:5px;color:;display: none\"></em>\n\t\t\t\t\t\t\t\t\t\t</span>\n\t\t\t\t\t\t\t\t\t\t\t\t\t\t\t\t\t\t친구가 되자 vol．3：브로콜리너마저 x 전기뱀장어\t\t\t\t\t\t\t\t\t<!--\t\t\t\t\t\t\t\t\t--><!--\t\t\t\t\t\t\t\t\t\t<span class=\"icons text-20 \"><i aria-hidden=\"true\" class=\"icon-picture\"></i></span>-->\n\t\t\t\t\t\t\t\t\t<!--\t\t\t\t\t\t\t\t\t--><!--\t\t\t\t\t\t\t\t\t--><!--\t\t\t\t\t\t\t\t\t\t<span class=\"icons text-20\"><i aria-hidden=\"true\" class=\"icon-folder\"></i></span>-->\n\t\t\t\t\t\t\t\t\t<!--\t\t\t\t\t\t\t\t\t--><!--\t\t\t\t\t\t\t\t\t--><!--\t\t\t\t\t\t\t\t\t\t<span class=\"icons text-20\"><i aria-hidden=\"true\" class=\"icon-camrecorder\"></i></span>-->\n\t\t\t\t\t\t\t\t\t<!--\t\t\t\t\t\t\t\t\t-->\t\t\t\t\t\t\t\t</div>\n\t\t\t\t\t\t\t\t\t\t\t\t\t\t\t\t\t<div class=\"text text-block show_body\">\n\t\t\t\t\t\t\t\t\t<span></span>\n\t\t\t\t\t\t\t\t</div>\n\t\t\t\t\t\t\t\t\t\t\t\t\t\t\t</div>\n\t\t\t\t\t\t\t\t\t\t\t\t\t\t\t\t\t\t\t\t</a>\n\t\t\t\t\t\t\t\t\t\t\t</span>\n\t\t\t\t</div>\n\t\t\t</div>","link":"https://festivallife.kr/concert/?q=YToxOntzOjEyOiJrZXl3b3JkX3R5cGUiO3M6MzoiYWxsIjt9&bmode=view&idx=17548812&t=board","retrieved":1704890127473,"image":"https://cdn.imweb.me/thumbnail/20240110/3fe482ed6d8c3.jpg"}]}